{"cameraMode":{"drawMode":0,"name":"Shaded","section":"Shading Mode"},"sceneLighting":false,"audioPlay":false,"sceneViewState":{"m_AlwaysRefresh":false,"showFog":true,"showSkybox":false,"showFlares":true,"showImageEffects":true,"showParticleSystems":true,"showVisualEffectGraphs":true,"m_FxEnabled":true},"in2DMode":false,"pivot":{"x":-0.3115454614162445,"y":-0.21802306175231934,"z":-0.7093335390090942},"rotation":{"x":0.0209229476749897,"y":0.9681133031845093,"z":-0.23415476083755494,"w":0.08650640398263931},"size":4.150815486907959,"orthographic":false}