{"cameraMode":{"drawMode":0,"name":"Shaded","section":"Shading Mode"},"sceneLighting":false,"audioPlay":false,"sceneViewState":{"m_AlwaysRefresh":false,"showFog":true,"showSkybox":false,"showFlares":true,"showImageEffects":true,"showParticleSystems":true,"showVisualEffectGraphs":true,"m_FxEnabled":true},"in2DMode":false,"pivot":{"x":-10.919034004211426,"y":14.504796981811524,"z":-2.6435093879699709},"rotation":{"x":0.09664252400398255,"y":-0.8526692390441895,"z":0.1700083315372467,"w":0.484641432762146},"size":40.516578674316409,"orthographic":false}